swimprotocol/__about__.py
swimprotocol/__init__.py
swimprotocol/address.py
swimprotocol/config.py
swimprotocol/listener.py
swimprotocol/members.py
swimprotocol/packet.py
swimprotocol/py.typed
swimprotocol/shuffle.py
swimprotocol/sign.py
swimprotocol/status.py
swimprotocol/sync.py
swimprotocol/tasks.py
swimprotocol/transport.py
swimprotocol/worker.py
swimprotocol/demo/__init__.py
swimprotocol/demo/changes.py
swimprotocol/demo/screen.py
swimprotocol/udp/__init__.py
swimprotocol/udp/config.py
swimprotocol/udp/pack.py
swimprotocol/udp/protocol.py
swimprotocol/udp/send.py
swim_protocol-0.6.3.dist-info/METADATA
swim_protocol-0.6.3.dist-info/WHEEL
swim_protocol-0.6.3.dist-info/entry_points.txt
swim_protocol-0.6.3.dist-info/licenses/LICENSE.md
swim_protocol-0.6.3.dist-info/RECORD
