Metadata-Version: 2.1
Name: swim-protocol
Version: 0.6.3
Summary: SWIM protocol implementation for exchanging cluster membership status and metadata.
Project-URL: Homepage, https://github.com/icgood/swim-protocol/
Project-URL: API Documentation, https://icgood.github.io/swim-protocol/
Author-email: Ian Good <ian@icgood.net>
License: ## MIT License
License-File: LICENSE.md
Classifier: Development Status :: 3 - Alpha
Classifier: Intended Audience :: Developers
Classifier: Intended Audience :: Information Technology
Classifier: License :: OSI Approved :: MIT License
Classifier: Programming Language :: Python
Classifier: Programming Language :: Python :: 3.10
Classifier: Programming Language :: Python :: 3.11
Requires-Python: ~=3.10
Requires-Dist: typing-extensions
Provides-Extra: dev
Requires-Dist: autopep8; extra == 'dev'
Requires-Dist: mypy; extra == 'dev'
Requires-Dist: pycodestyle; extra == 'dev'
Requires-Dist: pytest; extra == 'dev'
Requires-Dist: pytest-asyncio; extra == 'dev'
Requires-Dist: pytest-cov; extra == 'dev'
Requires-Dist: ruff; extra == 'dev'
Provides-Extra: doc
Requires-Dist: cloud-sptheme; extra == 'doc'
Requires-Dist: sphinx; extra == 'doc'
Requires-Dist: sphinx-autodoc-typehints; extra == 'doc'
